syslogng_kafka/__init__.py
syslogng_kafka/kafkadriver.py
syslogng_kafka/log.py
syslogng_kafka/util.py
syslogng_kafka-0.1.11.dist-info/DESCRIPTION.rst
syslogng_kafka-0.1.11.dist-info/METADATA
syslogng_kafka-0.1.11.dist-info/RECORD
syslogng_kafka-0.1.11.dist-info/WHEEL
syslogng_kafka-0.1.11.dist-info/metadata.json
syslogng_kafka-0.1.11.dist-info/top_level.txt
