Metadata-Version: 2.0
Name: syslogng-kafka
Version: 0.1.11
Summary: syslog-ng mod-python Kafka driver
Home-page: https://github.com/ilanddev/syslogng_kafka
Author: Julien Anguenot
Author-email: julien@anguenot.org
License: Apache Software License 2.0
Keywords: syslogng kafka
Platform: UNKNOWN
Classifier: Development Status :: 3 - Alpha
Classifier: Intended Audience :: System Administrators
Classifier: License :: OSI Approved :: Apache Software License
Classifier: Natural Language :: English
Classifier: Operating System :: POSIX :: Linux
Classifier: Programming Language :: Python :: 2
Classifier: Programming Language :: Python :: 2.7
Requires-Dist: confluent-kafka (==0.11.0)
Requires-Dist: syslog-rfc5424-formatter (>=1.0.0)
